{
  "metadata": {
    "total_items": 20,
    "sources": {
      "youtube": 10,
      "reddit": 10
    },
    "fetched_at": "2026-05-11T17:49:17.441879"
  },
  "data": {
    "youtube": [
      {
        "videoId": "dCY9xejoWDU",
        "title": "This Editing Workflow Saves Hours",
        "description": "Join Ground Control Film School Here: https://www.skool.com/gcfs/about ^ THE BEST DEAL on our Resolve Courses + Video ...",
        "channelTitle": "Casey Faris",
        "publishedAt": "2026-03-18T14:01:06Z",
        "url": "https://www.youtube.com/watch?v=dCY9xejoWDU",
        "fetched_at": "2026-05-11T17:49:09.007166"
      },
      {
        "videoId": "x3TrUPSFyPU",
        "title": "The Best Editing Workflow on the Internet",
        "description": "GET THE SPEED EDITING SYSTEM: https://www.justinnjames.com/speed-editing-v4- #videoediting #adobepremiere ...",
        "channelTitle": "Justin James",
        "publishedAt": "2026-02-11T15:57:00Z",
        "url": "https://www.youtube.com/watch?v=x3TrUPSFyPU",
        "fetched_at": "2026-05-11T17:49:09.007185"
      },
      {
        "videoId": "9a04BsKv26M",
        "title": "Top 5 Accounting Software for Small Business (2026 Guide)",
        "description": "My top 5 Accounting Software for Small Businesses. My recommended accounting software for small to medium businesses is ...",
        "channelTitle": "Stewart Gauld",
        "publishedAt": "2025-08-27T11:30:07Z",
        "url": "https://www.youtube.com/watch?v=9a04BsKv26M",
        "fetched_at": "2026-05-11T17:49:09.402621"
      },
      {
        "videoId": "Kb_x8MxKQ5w",
        "title": "What is the best accounting software for small businesses in 2026?",
        "description": "What is the best accounting software for small businesses in 2025? In this video, I am walking through 3 of my favourite ...",
        "channelTitle": "Jamie Trull",
        "publishedAt": "2024-12-04T18:00:12Z",
        "url": "https://www.youtube.com/watch?v=Kb_x8MxKQ5w",
        "fetched_at": "2026-05-11T17:49:09.402619"
      },
      {
        "videoId": "HdvTO9rvSm4",
        "title": "Best YouTube Editing Workflow in 2024! - DaVinci Resolve Video Editing Tips!",
        "description": "Join Ground Control Film School Here: https://www.skool.com/gcfs/about ^ THE BEST DEAL on our Resolve Courses + Video ...",
        "channelTitle": "Casey Faris",
        "publishedAt": "2024-01-27T14:30:04Z",
        "url": "https://www.youtube.com/watch?v=HdvTO9rvSm4",
        "fetched_at": "2026-05-11T17:49:09.007186"
      },
      {
        "videoId": "gOchfGvTogk",
        "title": "My simple video editing workflow | Make video editing easier!",
        "description": "Transform your photography today: https://www.scottedwardsyoutube.com Video editing is a craft. It takes a lot of time to make ...",
        "channelTitle": "Scott Edwards",
        "publishedAt": "2022-10-27T14:00:33Z",
        "url": "https://www.youtube.com/watch?v=gOchfGvTogk",
        "fetched_at": "2026-05-11T17:49:09.007183"
      },
      {
        "videoId": "pKpdibyljR4",
        "title": "The BOOKKEEPING BASICS for BEGINNERS",
        "description": "Bookkeeping is the recording of past financial data to make future business decisions. In this tutorial, you'll learn what ...",
        "channelTitle": "LYFE Accounting",
        "publishedAt": "2022-06-29T20:30:06Z",
        "url": "https://www.youtube.com/watch?v=pKpdibyljR4",
        "fetched_at": "2026-05-11T17:49:09.402615"
      },
      {
        "videoId": "UgMB5ReZxhk",
        "title": "Small Business EASY Bookkeeping How To! | Realistic Bookkeeping",
        "description": "This video is dedicated to explaining a super simple method of small business bookkeeping! I use this method of record keeping ...",
        "channelTitle": "Realistic Bookkeeping",
        "publishedAt": "2020-12-29T19:00:17Z",
        "url": "https://www.youtube.com/watch?v=UgMB5ReZxhk",
        "fetched_at": "2026-05-11T17:49:09.402601"
      },
      {
        "videoId": "3KeG7hHzUy4",
        "title": "Accounting Basics for Small Business Owners [By a CPA]",
        "description": "Learn the accounting basics for small business from a CPA. Today, you will learn the role of accounting in small business.",
        "channelTitle": "LYFE Accounting",
        "publishedAt": "2020-10-12T11:00:02Z",
        "url": "https://www.youtube.com/watch?v=3KeG7hHzUy4",
        "fetched_at": "2026-05-11T17:49:09.402617"
      },
      {
        "videoId": "Ve7C_0XpFmA",
        "title": "How To EDIT From START To FINISH - EDITING WORKFLOW",
        "description": "BACK TO SCHOOL SALE!!! NEW LIGHTROOM PRESETS ONLY $9.99! - https://goo.gl/YKAtkY Presets for your videos ONLY ...",
        "channelTitle": "Matti Haapoja",
        "publishedAt": "2017-08-29T15:51:01Z",
        "url": "https://www.youtube.com/watch?v=Ve7C_0XpFmA",
        "fetched_at": "2026-05-11T17:49:09.007180"
      }
    ],
    "reddit": [
      {
        "id": "9imfv9",
        "title": "Please Read This Before Posting or Commenting",
        "selftext": "**Violating [the rules of this subreddit](https://old.reddit.com/r/freelance/about/rules) will cause your post/comment will be removed and you will be banned PERMANENTLY. This is your only warning!** If you are unsure about whether a potential post or comment is suitable, [contact the moderators](https://www.reddit.com/message/compose?to=%2Fr%2Ffreelance) for guidance **before** posting it.\n\nIf you're asking a question, there's a good chance that it has already been answered! **[Read the wiki](/r/freelance/wiki/) and do a [search](https://www.reddit.com/r/freelance/search?q=&restrict_sr=on&sort=relevance&t=all) before submitting your post.**\n\nJust because your question involves freelancing does not mean that it is the best subreddit for it. Depending on your question, one of these other subreddits might be more appropriate:\n\n* /r/bigseo\n* /r/careerguidance\n* /r/copywriting\n* /r/DigitalNomad\n* /r/forhire\n* /r/freelanceUK\n* /r/freelanceWriters\n* /r/graphic_design\n* /r/jobs\n* /r/photography\n* /r/tax\n* /r/TranslationStudies\n* /r/UpWork\n* /r/videography\n* /r/webdev",
        "subreddit": "freelance",
        "author": "martey",
        "score": 531,
        "num_comments": 0,
        "created_utc": 1537827417.0,
        "permalink": "https://www.reddit.com/r/freelance/comments/9imfv9/please_read_this_before_posting_or_commenting/",
        "fetched_at": "2026-05-11T17:49:16.440471"
      },
      {
        "id": "1sndwq7",
        "title": "End of AI Slop",
        "selftext": "Hi r/SaaS community,\n\nWe think conventional methods aren't working in fighting the current state of AI slop in this sub. I know you are fed up with all this so am I. You come here to get real advice, listen to real people, and get real feedback - instead you get AI comments, bot DMs, disguised as real users which doesn't help you in your SaaS journey.\n\nWe are implementing captcha and user vetting bot, some of your posts and comments will get a comment from our bot and you will have to respond to the captcha, it is going to be random and limited not to be disruptive while repeated failures to complete this check will restrict/ban bot accounts and get reported. This minor discomfort will result in much better communication and substantially remove AI bots.\n\nMod team",
        "subreddit": "SaaS",
        "author": "Dubinko",
        "score": 276,
        "num_comments": 108,
        "created_utc": 1776368047.0,
        "permalink": "https://www.reddit.com/r/SaaS/comments/1sndwq7/end_of_ai_slop/",
        "fetched_at": "2026-05-11T17:49:11.623662"
      },
      {
        "id": "1t9bhls",
        "title": "I just made my first internet money ever and I couldn't be happier",
        "selftext": "The last couple of months, I had about 10 different real saas ideas. 7 of them I actually started building and only 4 were finished. From those 4 I only published 3 and only one, my current project did not fail immediately.\n\nI had huge problems with finding the right idea, I tried various different approaches like going through starter story or acquired or indiehacker searching for tools I liked to copy them and add a little twist, or I tried solving my own problems which worked for myself, but I couldn't make a real product out of those.\n\nI was really disappointed after my last fail, when I randomly checked twitter and I saw a viral post about a new tool that just got released and everyone went crazy in the comments saying how they liked the idea. So, I dug deeper and finally found something I could use, similar idea, but  different use case.\n\nI instantly started building and 2 weeks later I had my first prototype ready. I posted about it on reddit and after 3 days, someone actually bought a subscription.\n\nI was so happy, I couldn't believe what I was seeing,  because after all those months were I was trying to build something for people and no one cared, finally someone liked my product and decided to pay for it.\n\nSo the lesson is: Always keep going and never give up, just ship more and suddenly you will build something valuable. Every failed project has value for yourself and you will learn from it and why it failed.\n\nIf you have read so far and want to know what tool finally worked for me, [here](https://www.phaysr.com) is a link to my website. Maybe you will be my second customer ;)\n\nPS: I know I'm talking here like I just became a millionaire when in reality I just made 29 dollars. But we'll get there, step by step.",
        "subreddit": "SaaS",
        "author": "DrJonah345",
        "score": 208,
        "num_comments": 91,
        "created_utc": 1778430346.0,
        "permalink": "https://www.reddit.com/r/SaaS/comments/1t9bhls/i_just_made_my_first_internet_money_ever_and_i/",
        "fetched_at": "2026-05-11T17:49:11.623698"
      },
      {
        "id": "1ta1p0j",
        "title": "it's been 20 days, made 335$ with my seconds SaaS",
        "selftext": "So many fake posts on here, so I’ve attached the TrustMRR link in the comments   \n feel free to verify it yourself.\n\nThis is my second SaaS. My first one, FrameNet AI, did over $10K in total revenue, and I learned a lot from it   \n mostly what NOT to do. This time, I approached things differently.\n\nBefore launching, I started posting small glimpses of what I was building on r/sideproject short clips showing the actual output. That alone brought in a bunch of DMs and signups before I even had a launch date.\n\nLaunch day -  I didn’t do a huge announcement blast. I personally messaged every single person who had signed up or DM’d me. One by one. Sent emails too. From that alone, I got 2 major sales  one yearly plan and one monthly.\n\nAfter that, I created a proper demo video showing the full output quality and posted it on r/SideProject again. That brought in 2 more sales. Then more started coming from different places one from Twitter, one through a friend’s referral, and one from posting on a competitor’s subreddit as an alternative.\n\nThe most surprising part: I have 3 pricing tiers, and almost everyone went straight for the $35/month mid-tier plan instead of the cheapest one. One person even upgraded to the $75/month plan after trying it.\n\nThe best thing that happened was one user who got so impressed with the output that he started sharing it with his team. Then his team started using it too. He basically became our internal marketer inside his company without me even asking. That one person’s word-of-mouth has been worth more than any post I’ve made so far. (Currently waiting on a potential B2B deal.)\n\n**What I built: DistilBook**  \nIt takes your documents and turns them into actual animated explainer videos . It works exceptionally well with technical material.\n\nSo far, people are using it for:\n\n* Product walkthroughs\n* Onboarding material\n* Technical documentation\n* Religious educational content in multiple languages\n\nWhat I’m doing now: cold emails, Twitter posting, and Reddit marketing. Let’s see how it goes.\n\nIf you’re interested: distilbook(.)com\n\nTrustMRR link is in the comments. Happy to answer anything.",
        "subreddit": "SaaS",
        "author": "ajithpinninti",
        "score": 126,
        "num_comments": 53,
        "created_utc": 1778502153.0,
        "permalink": "https://www.reddit.com/r/SaaS/comments/1ta1p0j/its_been_20_days_made_335_with_my_seconds_saas/",
        "fetched_at": "2026-05-11T17:49:11.623666"
      },
      {
        "id": "1sx8v2m",
        "title": "Is it okay to ask for a contract after I started work?",
        "selftext": "Boss missed payday and told me he’s busy and to be patient. I’m getting $100 a week, do you think it’s okay to ask for a contract to enforce payday?\n\n  \nEDIT: Hey all. Thank you for responding to this. I asked for a contract and he fired me lol. So anyway I went into his fan disc and exposed his ass for not paying his employees (he's a YTuber) Pretty much everyone was on my side. There's a lot more context behind this post but I'm not going to get into it as the matter if pretty much resolved for now. Thank you again!",
        "subreddit": "freelance",
        "author": "Aur0ha",
        "score": 120,
        "num_comments": 65,
        "created_utc": 1777307517.0,
        "permalink": "https://www.reddit.com/r/freelance/comments/1sx8v2m/is_it_okay_to_ask_for_a_contract_after_i_started/",
        "fetched_at": "2026-05-11T17:49:16.440509"
      },
      {
        "id": "1se54l6",
        "title": "Do people actually get hired and paid from Reddit freelance jobs?",
        "selftext": "Hi everyone. I’m new to freelancing on Reddit and trying to understand how things really work here.\n\nI’ve seen many job posts across different subreddits offering small freelance or online tasks, but I’m wondering how often people actually get hired and successfully paid. Are these opportunities generally reliable for beginners, or does it take a long time before landing your first paid task? And how do you sift out the scams from the real ones coz some of these posts look very convincing at face-value.\n\nI’d really appreciate hearing about your experiences, especially any advice for someone just starting out and trying to avoid scams while building credibility. Thank you!",
        "subreddit": "freelance",
        "author": "Decent-Touch5292",
        "score": 89,
        "num_comments": 132,
        "created_utc": 1775495852.0,
        "permalink": "https://www.reddit.com/r/freelance/comments/1se54l6/do_people_actually_get_hired_and_paid_from_reddit/",
        "fetched_at": "2026-05-11T17:49:16.440534"
      },
      {
        "id": "1swge6q",
        "title": "Gotta say thanks to Reddit.",
        "selftext": "Hello guys, just wanted to share that after posting so many posts about my freelance services, I got my first client on Saturday and all thanks to Reddit. 💗\n\nThe client is nice and respectful towards me even tho I'm a beginner she trusts me and helps me whenever I need her help. After having so many weird experiences where some people ghosted me at the stage where they were supposed to pay me, NSFW, feet pics, personal modeling texts, I actually got someone who is straightforward and trustworthy, even tho it's a short project I'm learning new things and trying to become a better version of myself. \n\nAll I can say is this platform can be used as your strength if you want it in that way. \n\nI have to find someone trustworthy again after her project ends tho.😭",
        "subreddit": "freelance",
        "author": "No_Summer_7639",
        "score": 84,
        "num_comments": 11,
        "created_utc": 1777230252.0,
        "permalink": "https://www.reddit.com/r/freelance/comments/1swge6q/gotta_say_thanks_to_reddit/",
        "fetched_at": "2026-05-11T17:49:16.440511"
      },
      {
        "id": "1sxer6j",
        "title": "Client paid me $1500 then disappeared… do I follow up or just leave it?",
        "selftext": "&#x200B;\n\nI need outside opinions because I feel weird about this\n\nSo I’m a social media manager/strategist. Last December a girl I kinda know (we’ve interacted a lot online, same industry, she’s more senior than me, has her own agency) reached out to me for services\n\nShe signed up for a 3 month package ($1500 total), paid upfront, everything was clear. I started the first month, sent ideas, did my part\n\nThen she kinda disappeared\n\nAbout a month in, she messaged saying her kid is going through mental health stuff and she hasn’t been able to focus on work. Totally valid, I told her to prioritize her family.\n\nBut now it’s been months. Like… a while. And nothing since.\n\nNo approvals, no feedback, no “pause,” no “continue,” nothing\n\nAnd I’m stuck in this awkward spot:\n\nI don’t want to keep messaging and feel like I’m bothering her during a hard time\n\nI don’t want her to feel like I took her money and did nothing\n\nI also don’t know if she secretly didn’t like the work and is avoiding the convo\n\nAnd I’m not used to this situation because usually clients are the opposite (very on top of me lol)\n\nPart of me is like: just leave it, she can come back anytime and use the package\n\nPart of me is like: this is $1500… should I be more proactive? Offer a refund? Set a boundary? Pause officially?\n\nIt’s also tricky because I know her, so it’s not purely transactional\n\nWhat would you do in this situation?\n\nFollow up again?\n\nLeave it alone?\n\nOffer partial refund?\n\nOr set a “use it by X date” type boundary?\n\nI don’t want to handle this in a way that feels insensitive, but I also don’t want this to stay in limbo forever",
        "subreddit": "freelance",
        "author": "igetyourbrand",
        "score": 80,
        "num_comments": 100,
        "created_utc": 1777319779.0,
        "permalink": "https://www.reddit.com/r/freelance/comments/1sxer6j/client_paid_me_1500_then_disappeared_do_i_follow/",
        "fetched_at": "2026-05-11T17:49:16.440507"
      },
      {
        "id": "1t9npt0",
        "title": "Are paper business cards kinda pointless now or is it just me?",
        "selftext": "So I was at this networking event last week and I realized I’m still carrying around a stack of paper business cards like it’s 2005. Half the time they either get lost in my bag or I end up typing all the info into my phone anyway. Plus, let’s be real, most people probably just toss them. \n\nHas anyone switched to digital business cards? Are they actually worth it? Lowkey feel like I need to update my whole networking game.",
        "subreddit": "smallbusiness",
        "author": "theceoinprogress",
        "score": 77,
        "num_comments": 144,
        "created_utc": 1778459414.0,
        "permalink": "https://www.reddit.com/r/smallbusiness/comments/1t9npt0/are_paper_business_cards_kinda_pointless_now_or/",
        "fetched_at": "2026-05-11T17:49:14.674157"
      },
      {
        "id": "1seqrgk",
        "title": "how \"free work\" turned into my best paying clients, i know this sounds backwards",
        "selftext": "i know free work gets bad rep here and for good reason. but want to share what worked for me because context matters.\n\nim a developer based in india. started approaching local businesses offering to build them a v1 of whatever they needed. website, ordering system, booking page. completly free no strings.\n\nmy logic was simple. i needed real projects, real case studies and real referrals. not another todo app on my portfolio lol.\n\nwhat happend:\n\nout of about 15 businesses i helped, 4 came back for paid work within a month. \"can you add this feature\" or \"my friend needs something similar\"\n\n3 became ongoing with monthly retainers for maintainance and updates\n\nthe case studies helped me close a client in a completely different city without even meeting them\n\nkey thing, i only offered free work to businesses i genuinly wanted to work with. passionate owners doing interesting things. not anyone who just wanted cheap labor.\n\nits not for everyone. but if you're early and need momentum, strategically free beats cold pitching strangers everytime.\n\n",
        "subreddit": "freelance",
        "author": "sadiqueb",
        "score": 77,
        "num_comments": 74,
        "created_utc": 1775552961.0,
        "permalink": "https://www.reddit.com/r/freelance/comments/1seqrgk/how_free_work_turned_into_my_best_paying_clients/",
        "fetched_at": "2026-05-11T17:49:16.440528"
      }
    ]
  }
}